{
    "metadata": {
        "startTime": 1718940616222,
        "interval": 4000,
        "platform": {
            "type": 0,
            "version": "4223-Spigot-146439e-d01c70e (MC: 1.21)",
            "minecraftVersion": "v1_21_R1",
            "sparkVersion": 2
        },
        "platformStatistics": {
            "memory": {
                "heap": {
                    "used": 466494672,
                    "total": 897581056
                }
            },
            "gc": {
                "G1 Young Generation": {
                    "total": 316,
                    "avgTime": 20.60759493670886,
                    "avgFrequency": 69039
                },
                "G1 Concurrent GC": {
                    "total": 218,
                    "avgTime": 6.545871559633028,
                    "avgFrequency": 100098
                },
                "G1 Old Generation": {
                    "total": 0,
                    "avgTime": 0,
                    "avgFrequency": 0
                }
            },
            "uptime": 21822837,
            "tps": {
                "last1m": 19.999992627336052,
                "last5m": 20.00000601280181,
                "last15m": 20.000000377088895
            },
            "playerCount": 1,
            "world": {
                "totalEntities": 264,
                "entityCounts": {
                    "chicken": 1,
                    "bee": 1,
                    "axolotl": 2,
                    "cow": 1,
                    "chest_minecart": 5,
                    "pig": 2,
                    "allay": 2,
                    "skeleton": 18,
                    "bat": 16,
                    "camel": 1,
                    "end_crystal": 10,
                    "cat": 5,
                    "zombie": 21,
                    "armor_stand": 2,
                    "sheep": 17,
                    "player": 1,
                    "item": 2,
                    "salmon": 10,
                    "zombie_villager": 2,
                    "chest_boat": 2,
                    "boat": 4,
                    "strider": 4,
                    "horse": 3,
                    "ender_dragon": 1,
                    "leash_knot": 4,
                    "cod": 12,
                    "glow_squid": 5,
                    "squid": 8,
                    "spider": 4,
                    "creeper": 26,
                    "enderman": 72
                },
                "worlds": [
                    {
                        "totalEntities": 182,
                        "regions": [
                            {
                                "totalEntities": 1,
                                "chunks": [
                                    {
                                        "x": 3,
                                        "z": -2,
                                        "totalEntities": 1,
                                        "entityCounts": {
                                            "bee": 1
                                        }
                                    }
                                ]
                            },
                            {
                                "totalEntities": 2,
                                "chunks": [
                                    {
                                        "x": 5,
                                        "z": 0,
                                        "totalEntities": 1,
                                        "entityCounts": {
                                            "cow": 1
                                        }
                                    },
                                    {
                                        "x": 6,
                                        "z": 0,
                                        "totalEntities": 1,
                                        "entityCounts": {
                                            "enderman": 1
                                        }
                                    }
                                ]
                            },
                            {
                                "totalEntities": 1,
                                "chunks": [
                                    {
                                        "x": 6,
                                        "z": 3,
                                        "totalEntities": 1,
                                        "entityCounts": {
                                            "chicken": 1
                                        }
                                    }
                                ]
                            },
                            {
                                "totalEntities": 2,
                                "chunks": [
                                    {
                                        "x": 12,
                                        "z": 11,
                                        "totalEntities": 2,
                                        "entityCounts": {
                                            "axolotl": 2
                                        }
                                    }
                                ]
                            },
                            {
                                "totalEntities": 155,
                                "chunks": [
                                    {
                                        "x": 4,
                                        "z": 20,
                                        "totalEntities": 2,
                                        "entityCounts": {
                                            "bat": 2
                                        }
                                    },
                                    {
                                        "x": 5,
                                        "z": 21,
                                        "totalEntities": 5,
                                        "entityCounts": {
                                            "chest_minecart": 1,
                                            "creeper": 1,
                                            "skeleton": 1,
                                            "enderman": 1,
                                            "bat": 1
                                        }
                                    },
                                    {
                                        "x": 6,
                                        "z": 22,
                                        "totalEntities": 1,
                                        "entityCounts": {
                                            "creeper": 1
                                        }
                                    },
                                    {
                                        "x": 7,
                                        "z": 23,
                                        "totalEntities": 1,
                                        "entityCounts": {
                                            "squid": 1
                                        }
                                    },
                                    {
                                        "x": 4,
                                        "z": 21,
                                        "totalEntities": 3,
                                        "entityCounts": {
                                            "creeper": 2,
                                            "bat": 1
                                        }
                                    },
                                    {
                                        "x": 5,
                                        "z": 20,
                                        "totalEntities": 1,
                                        "entityCounts": {
                                            "bat": 1
                                        }
                                    },
                                    {
                                        "x": 6,
                                        "z": 23,
                                        "totalEntities": 2,
                                        "entityCounts": {
                                            "creeper": 1,
                                            "spider": 1
                                        }
                                    },
                                    {
                                        "x": 0,
                                        "z": 17,
                                        "totalEntities": 3,
                                        "entityCounts": {
                                            "zombie_villager": 1,
                                            "creeper": 1,
                                            "zombie": 1
                                        }
                                    },
                                    {
                                        "x": 4,
                                        "z": 22,
                                        "totalEntities": 2,
                                        "entityCounts": {
                                            "creeper": 2
                                        }
                                    },
                                    {
                                        "x": 5,
                                        "z": 23,
                                        "totalEntities": 2,
                                        "entityCounts": {
                                            "spider": 1,
                                            "bat": 1
                                        }
                                    },
                                    {
                                        "x": 6,
                                        "z": 20,
                                        "totalEntities": 1,
                                        "entityCounts": {
                                            "chest_minecart": 1
                                        }
                                    },
                                    {
                                        "x": 0,
                                        "z": 18,
                                        "totalEntities": 1,
                                        "entityCounts": {
                                            "creeper": 1
                                        }
                                    },
                                    {
                                        "x": 4,
                                        "z": 23,
                                        "totalEntities": 1,
                                        "entityCounts": {
                                            "zombie": 1
                                        }
                                    },
                                    {
                                        "x": 5,
                                        "z": 22,
                                        "totalEntities": 4,
                                        "entityCounts": {
                                            "creeper": 3,
                                            "zombie": 1
                                        }
                                    },
                                    {
                                        "x": 0,
                                        "z": 19,
                                        "totalEntities": 4,
                                        "entityCounts": {
                                            "cod": 3,
                                            "salmon": 1
                                        }
                                    },
                                    {
                                        "x": 6,
                                        "z": 21,
                                        "totalEntities": 5,
                                        "entityCounts": {
                                            "creeper": 1,
                                            "zombie": 4
                                        }
                                    },
                                    {
                                        "x": 7,
                                        "z": 20,
                                        "totalEntities": 1,
                                        "entityCounts": {
                                            "chest_minecart": 1
                                        }
                                    },
                                    {
                                        "x": 2,
                                        "z": 22,
                                        "totalEntities": 2,
                                        "entityCounts": {
                                            "zombie_villager": 1,
                                            "skeleton": 1
                                        }
                                    },
                                    {
                                        "x": 0,
                                        "z": 20,
                                        "totalEntities": 5,
                                        "entityCounts": {
                                            "salmon": 5
                                        }
                                    },
                                    {
                                        "x": 2,
                                        "z": 23,
                                        "totalEntities": 2,
                                        "entityCounts": {
                                            "zombie": 2
                                        }
                                    },
                                    {
                                        "x": 3,
                                        "z": 22,
                                        "totalEntities": 1,
                                        "entityCounts": {
                                            "creeper": 1
                                        }
                                    },
                                    {
                                        "x": 0,
                                        "z": 21,
                                        "totalEntities": 6,
                                        "entityCounts": {
                                            "cod": 3,
                                            "salmon": 3
                                        }
                                    },
                                    {
                                        "x": 1,
                                        "z": 20,
                                        "totalEntities": 7,
                                        "entityCounts": {
                                            "cod": 6,
                                            "salmon": 1
                                        }
                                    },
                                    {
                                        "x": -2,
                                        "z": 23,
                                        "totalEntities": 1,
                                        "entityCounts": {
                                            "bat": 1
                                        }
                                    },
                                    {
                                        "x": 1,
                                        "z": 23,
                                        "totalEntities": 3,
                                        "entityCounts": {
                                            "item": 1,
                                            "creeper": 1,
                                            "skeleton": 1
                                        }
                                    },
                                    {
                                        "x": -1,
                                        "z": 22,
                                        "totalEntities": 1,
                                        "entityCounts": {
                                            "glow_squid": 1
                                        }
                                    },
                                    {
                                        "x": 3,
                                        "z": 21,
                                        "totalEntities": 6,
                                        "entityCounts": {
                                            "skeleton": 1,
                                            "bat": 3,
                                            "pig": 1,
                                            "sheep": 1
                                        }
                                    },
                                    {
                                        "x": 5,
                                        "z": 19,
                                        "totalEntities": 3,
                                        "entityCounts": {
                                            "creeper": 2,
                                            "sheep": 1
                                        }
                                    },
                                    {
                                        "x": -1,
                                        "z": 23,
                                        "totalEntities": 3,
                                        "entityCounts": {
                                            "leash_knot": 1,
                                            "creeper": 1,
                                            "sheep": 1
                                        }
                                    },
                                    {
                                        "x": 0,
                                        "z": 23,
                                        "totalEntities": 3,
                                        "entityCounts": {
                                            "item": 1,
                                            "creeper": 2
                                        }
                                    },
                                    {
                                        "x": 1,
                                        "z": 22,
                                        "totalEntities": 3,
                                        "entityCounts": {
                                            "skeleton": 1,
                                            "zombie": 1,
                                            "player": 1
                                        }
                                    },
                                    {
                                        "x": 2,
                                        "z": 21,
                                        "totalEntities": 1,
                                        "entityCounts": {
                                            "creeper": 1
                                        }
                                    },
                                    {
                                        "x": 3,
                                        "z": 20,
                                        "totalEntities": 1,
                                        "entityCounts": {
                                            "sheep": 1
                                        }
                                    },
                                    {
                                        "x": -2,
                                        "z": 25,
                                        "totalEntities": 5,
                                        "entityCounts": {
                                            "boat": 2,
                                            "horse": 1,
                                            "cat": 1,
                                            "chest_boat": 1
                                        }
                                    },
                                    {
                                        "x": -1,
                                        "z": 24,
                                        "totalEntities": 1,
                                        "entityCounts": {
                                            "cat": 1
                                        }
                                    },
                                    {
                                        "x": 0,
                                        "z": 24,
                                        "totalEntities": 1,
                                        "entityCounts": {
                                            "skeleton": 1
                                        }
                                    },
                                    {
                                        "x": 1,
                                        "z": 25,
                                        "totalEntities": 1,
                                        "entityCounts": {
                                            "bat": 1
                                        }
                                    },
                                    {
                                        "x": 3,
                                        "z": 27,
                                        "totalEntities": 1,
                                        "entityCounts": {
                                            "creeper": 1
                                        }
                                    },
                                    {
                                        "x": -4,
                                        "z": 26,
                                        "totalEntities": 3,
                                        "entityCounts": {
                                            "squid": 3
                                        }
                                    },
                                    {
                                        "x": -1,
                                        "z": 25,
                                        "totalEntities": 1,
                                        "entityCounts": {
                                            "camel": 1
                                        }
                                    },
                                    {
                                        "x": 0,
                                        "z": 25,
                                        "totalEntities": 1,
                                        "entityCounts": {
                                            "bat": 1
                                        }
                                    },
                                    {
                                        "x": 2,
                                        "z": 27,
                                        "totalEntities": 4,
                                        "entityCounts": {
                                            "creeper": 1,
                                            "spider": 1,
                                            "zombie": 2
                                        }
                                    },
                                    {
                                        "x": -2,
                                        "z": 27,
                                        "totalEntities": 5,
                                        "entityCounts": {
                                            "leash_knot": 1,
                                            "enderman": 1,
                                            "cat": 1,
                                            "allay": 2
                                        }
                                    },
                                    {
                                        "x": -1,
                                        "z": 26,
                                        "totalEntities": 3,
                                        "entityCounts": {
                                            "leash_knot": 1,
                                            "horse": 2
                                        }
                                    },
                                    {
                                        "x": -4,
                                        "z": 25,
                                        "totalEntities": 1,
                                        "entityCounts": {
                                            "squid": 1
                                        }
                                    },
                                    {
                                        "x": 0,
                                        "z": 26,
                                        "totalEntities": 3,
                                        "entityCounts": {
                                            "boat": 1,
                                            "skeleton": 1,
                                            "zombie": 1
                                        }
                                    },
                                    {
                                        "x": 1,
                                        "z": 27,
                                        "totalEntities": 1,
                                        "entityCounts": {
                                            "zombie": 1
                                        }
                                    },
                                    {
                                        "x": 3,
                                        "z": 25,
                                        "totalEntities": 2,
                                        "entityCounts": {
                                            "skeleton": 1,
                                            "bat": 1
                                        }
                                    },
                                    {
                                        "x": -2,
                                        "z": 26,
                                        "totalEntities": 2,
                                        "entityCounts": {
                                            "leash_knot": 1,
                                            "cat": 1
                                        }
                                    },
                                    {
                                        "x": -1,
                                        "z": 27,
                                        "totalEntities": 2,
                                        "entityCounts": {
                                            "enderman": 1,
                                            "cat": 1
                                        }
                                    },
                                    {
                                        "x": -3,
                                        "z": 25,
                                        "totalEntities": 1,
                                        "entityCounts": {
                                            "chest_boat": 1
                                        }
                                    },
                                    {
                                        "x": 0,
                                        "z": 27,
                                        "totalEntities": 1,
                                        "entityCounts": {
                                            "bat": 1
                                        }
                                    },
                                    {
                                        "x": 1,
                                        "z": 26,
                                        "totalEntities": 1,
                                        "entityCounts": {
                                            "zombie": 1
                                        }
                                    },
                                    {
                                        "x": 3,
                                        "z": 24,
                                        "totalEntities": 3,
                                        "entityCounts": {
                                            "creeper": 1,
                                            "bat": 1,
                                            "glow_squid": 1
                                        }
                                    },
                                    {
                                        "x": -1,
                                        "z": 28,
                                        "totalEntities": 5,
                                        "entityCounts": {
                                            "armor_stand": 1,
                                            "creeper": 1,
                                            "skeleton": 3
                                        }
                                    },
                                    {
                                        "x": 0,
                                        "z": 28,
                                        "totalEntities": 1,
                                        "entityCounts": {
                                            "skeleton": 1
                                        }
                                    },
                                    {
                                        "x": -5,
                                        "z": 24,
                                        "totalEntities": 1,
                                        "entityCounts": {
                                            "squid": 1
                                        }
                                    },
                                    {
                                        "x": 4,
                                        "z": 24,
                                        "totalEntities": 1,
                                        "entityCounts": {
                                            "glow_squid": 1
                                        }
                                    },
                                    {
                                        "x": 5,
                                        "z": 25,
                                        "totalEntities": 1,
                                        "entityCounts": {
                                            "zombie": 1
                                        }
                                    },
                                    {
                                        "x": -2,
                                        "z": 28,
                                        "totalEntities": 1,
                                        "entityCounts": {
                                            "armor_stand": 1
                                        }
                                    },
                                    {
                                        "x": -5,
                                        "z": 25,
                                        "totalEntities": 2,
                                        "entityCounts": {
                                            "squid": 2
                                        }
                                    },
                                    {
                                        "x": 5,
                                        "z": 24,
                                        "totalEntities": 2,
                                        "entityCounts": {
                                            "zombie": 1,
                                            "glow_squid": 1
                                        }
                                    },
                                    {
                                        "x": 4,
                                        "z": 26,
                                        "totalEntities": 2,
                                        "entityCounts": {
                                            "skeleton": 1,
                                            "bat": 1
                                        }
                                    },
                                    {
                                        "x": 6,
                                        "z": 24,
                                        "totalEntities": 2,
                                        "entityCounts": {
                                            "skeleton": 2
                                        }
                                    },
                                    {
                                        "x": 6,
                                        "z": 25,
                                        "totalEntities": 6,
                                        "entityCounts": {
                                            "skeleton": 2,
                                            "spider": 1,
                                            "zombie": 3
                                        }
                                    },
                                    {
                                        "x": 8,
                                        "z": 23,
                                        "totalEntities": 1,
                                        "entityCounts": {
                                            "chest_minecart": 1
                                        }
                                    }
                                ]
                            },
                            {
                                "totalEntities": 1,
                                "chunks": [
                                    {
                                        "x": 1,
                                        "z": 30,
                                        "totalEntities": 1,
                                        "entityCounts": {
                                            "enderman": 1
                                        }
                                    }
                                ]
                            },
                            {
                                "totalEntities": 14,
                                "chunks": [
                                    {
                                        "x": -5,
                                        "z": 21,
                                        "totalEntities": 2,
                                        "entityCounts": {
                                            "creeper": 1,
                                            "skeleton": 1
                                        }
                                    },
                                    {
                                        "x": -6,
                                        "z": 20,
                                        "totalEntities": 1,
                                        "entityCounts": {
                                            "boat": 1
                                        }
                                    },
                                    {
                                        "x": -7,
                                        "z": 20,
                                        "totalEntities": 11,
                                        "entityCounts": {
                                            "sheep": 11
                                        }
                                    }
                                ]
                            },
                            {
                                "totalEntities": 2,
                                "chunks": [
                                    {
                                        "x": -10,
                                        "z": 21,
                                        "totalEntities": 1,
                                        "entityCounts": {
                                            "sheep": 1
                                        }
                                    },
                                    {
                                        "x": -10,
                                        "z": 22,
                                        "totalEntities": 1,
                                        "entityCounts": {
                                            "sheep": 1
                                        }
                                    }
                                ]
                            },
                            {
                                "totalEntities": 1,
                                "chunks": [
                                    {
                                        "x": -11,
                                        "z": 19,
                                        "totalEntities": 1,
                                        "entityCounts": {
                                            "pig": 1
                                        }
                                    }
                                ]
                            },
                            {
                                "totalEntities": 2,
                                "chunks": [
                                    {
                                        "x": 3,
                                        "z": 17,
                                        "totalEntities": 2,
                                        "entityCounts": {
                                            "zombie": 1,
                                            "glow_squid": 1
                                        }
                                    }
                                ]
                            },
                            {
                                "totalEntities": 1,
                                "chunks": [
                                    {
                                        "x": 7,
                                        "z": 17,
                                        "totalEntities": 1,
                                        "entityCounts": {
                                            "chest_minecart": 1
                                        }
                                    }
                                ]
                            }
                        ]
                    },
                    {
                        "totalEntities": 58,
                        "regions": [
                            {
                                "totalEntities": 54,
                                "chunks": [
                                    {
                                        "x": 1,
                                        "z": 1,
                                        "totalEntities": 4,
                                        "entityCounts": {
                                            "enderman": 4
                                        }
                                    },
                                    {
                                        "x": 1,
                                        "z": -2,
                                        "totalEntities": 1,
                                        "entityCounts": {
                                            "enderman": 1
                                        }
                                    },
                                    {
                                        "x": 2,
                                        "z": 2,
                                        "totalEntities": 3,
                                        "entityCounts": {
                                            "enderman": 3
                                        }
                                    },
                                    {
                                        "x": 2,
                                        "z": -3,
                                        "totalEntities": 2,
                                        "entityCounts": {
                                            "enderman": 2
                                        }
                                    },
                                    {
                                        "x": 3,
                                        "z": 3,
                                        "totalEntities": 1,
                                        "entityCounts": {
                                            "enderman": 1
                                        }
                                    },
                                    {
                                        "x": 0,
                                        "z": 1,
                                        "totalEntities": 3,
                                        "entityCounts": {
                                            "enderman": 3
                                        }
                                    },
                                    {
                                        "x": 1,
                                        "z": 0,
                                        "totalEntities": 1,
                                        "entityCounts": {
                                            "enderman": 1
                                        }
                                    },
                                    {
                                        "x": 3,
                                        "z": 2,
                                        "totalEntities": 1,
                                        "entityCounts": {
                                            "enderman": 1
                                        }
                                    },
                                    {
                                        "x": -1,
                                        "z": 2,
                                        "totalEntities": 1,
                                        "entityCounts": {
                                            "end_crystal": 1
                                        }
                                    },
                                    {
                                        "x": 0,
                                        "z": 2,
                                        "totalEntities": 1,
                                        "entityCounts": {
                                            "end_crystal": 1
                                        }
                                    },
                                    {
                                        "x": 2,
                                        "z": -1,
                                        "totalEntities": 4,
                                        "entityCounts": {
                                            "enderman": 4
                                        }
                                    },
                                    {
                                        "x": 2,
                                        "z": 0,
                                        "totalEntities": 1,
                                        "entityCounts": {
                                            "end_crystal": 1
                                        }
                                    },
                                    {
                                        "x": 0,
                                        "z": -3,
                                        "totalEntities": 1,
                                        "entityCounts": {
                                            "end_crystal": 1
                                        }
                                    },
                                    {
                                        "x": -1,
                                        "z": -3,
                                        "totalEntities": 1,
                                        "entityCounts": {
                                            "end_crystal": 1
                                        }
                                    },
                                    {
                                        "x": 1,
                                        "z": 3,
                                        "totalEntities": 4,
                                        "entityCounts": {
                                            "enderman": 4
                                        }
                                    },
                                    {
                                        "x": 3,
                                        "z": 1,
                                        "totalEntities": 5,
                                        "entityCounts": {
                                            "enderman": 5
                                        }
                                    },
                                    {
                                        "x": 2,
                                        "z": -2,
                                        "totalEntities": 2,
                                        "entityCounts": {
                                            "enderman": 1,
                                            "end_crystal": 1
                                        }
                                    },
                                    {
                                        "x": 2,
                                        "z": 1,
                                        "totalEntities": 5,
                                        "entityCounts": {
                                            "enderman": 4,
                                            "end_crystal": 1
                                        }
                                    },
                                    {
                                        "x": 1,
                                        "z": -3,
                                        "totalEntities": 6,
                                        "entityCounts": {
                                            "enderman": 6
                                        }
                                    },
                                    {
                                        "x": 3,
                                        "z": -1,
                                        "totalEntities": 6,
                                        "entityCounts": {
                                            "enderman": 6
                                        }
                                    },
                                    {
                                        "x": 3,
                                        "z": 0,
                                        "totalEntities": 1,
                                        "entityCounts": {
                                            "enderman": 1
                                        }
                                    }
                                ]
                            },
                            {
                                "totalEntities": 4,
                                "chunks": [
                                    {
                                        "x": -2,
                                        "z": 0,
                                        "totalEntities": 1,
                                        "entityCounts": {
                                            "ender_dragon": 1
                                        }
                                    },
                                    {
                                        "x": -3,
                                        "z": -1,
                                        "totalEntities": 1,
                                        "entityCounts": {
                                            "end_crystal": 1
                                        }
                                    },
                                    {
                                        "x": -3,
                                        "z": -2,
                                        "totalEntities": 1,
                                        "entityCounts": {
                                            "end_crystal": 1
                                        }
                                    },
                                    {
                                        "x": -3,
                                        "z": 1,
                                        "totalEntities": 1,
                                        "entityCounts": {
                                            "end_crystal": 1
                                        }
                                    }
                                ]
                            }
                        ]
                    },
                    {
                        "totalEntities": 24,
                        "regions": [
                            {
                                "totalEntities": 15,
                                "chunks": [
                                    {
                                        "x": -2,
                                        "z": 1,
                                        "totalEntities": 2,
                                        "entityCounts": {
                                            "enderman": 2
                                        }
                                    },
                                    {
                                        "x": -2,
                                        "z": -2,
                                        "totalEntities": 1,
                                        "entityCounts": {
                                            "enderman": 1
                                        }
                                    },
                                    {
                                        "x": -1,
                                        "z": 1,
                                        "totalEntities": 1,
                                        "entityCounts": {
                                            "enderman": 1
                                        }
                                    },
                                    {
                                        "x": -1,
                                        "z": 2,
                                        "totalEntities": 1,
                                        "entityCounts": {
                                            "enderman": 1
                                        }
                                    },
                                    {
                                        "x": 0,
                                        "z": 2,
                                        "totalEntities": 1,
                                        "entityCounts": {
                                            "enderman": 1
                                        }
                                    },
                                    {
                                        "x": -3,
                                        "z": 0,
                                        "totalEntities": 4,
                                        "entityCounts": {
                                            "enderman": 4
                                        }
                                    },
                                    {
                                        "x": -3,
                                        "z": -1,
                                        "totalEntities": 1,
                                        "entityCounts": {
                                            "enderman": 1
                                        }
                                    },
                                    {
                                        "x": -1,
                                        "z": -3,
                                        "totalEntities": 3,
                                        "entityCounts": {
                                            "strider": 3
                                        }
                                    },
                                    {
                                        "x": -2,
                                        "z": -3,
                                        "totalEntities": 1,
                                        "entityCounts": {
                                            "enderman": 1
                                        }
                                    }
                                ]
                            },
                            {
                                "totalEntities": 7,
                                "chunks": [
                                    {
                                        "x": 1,
                                        "z": -2,
                                        "totalEntities": 1,
                                        "entityCounts": {
                                            "enderman": 1
                                        }
                                    },
                                    {
                                        "x": 1,
                                        "z": 0,
                                        "totalEntities": 3,
                                        "entityCounts": {
                                            "enderman": 2,
                                            "strider": 1
                                        }
                                    },
                                    {
                                        "x": 2,
                                        "z": -1,
                                        "totalEntities": 1,
                                        "entityCounts": {
                                            "enderman": 1
                                        }
                                    },
                                    {
                                        "x": 3,
                                        "z": -1,
                                        "totalEntities": 2,
                                        "entityCounts": {
                                            "enderman": 2
                                        }
                                    }
                                ]
                            },
                            {
                                "totalEntities": 1,
                                "chunks": [
                                    {
                                        "x": 3,
                                        "z": -3,
                                        "totalEntities": 1,
                                        "entityCounts": {
                                            "enderman": 1
                                        }
                                    }
                                ]
                            },
                            {
                                "totalEntities": 1,
                                "chunks": [
                                    {
                                        "x": 3,
                                        "z": 3,
                                        "totalEntities": 1,
                                        "entityCounts": {
                                            "enderman": 1
                                        }
                                    }
                                ]
                            }
                        ]
                    }
                ]
            }
        },
        "systemStatistics": {
            "cpu": {
                "threads": 4,
                "processUsage": {
                    "last1m": 0.074125,
                    "last15m": 0.07686944444444445
                },
                "systemUsage": {
                    "last1m": 0.07415415833333333,
                    "last15m": 0.07687648222222222
                },
                "modelName": "Intel(R) Xeon(R) CPU E5-2650 v4 @ 2.20GHz"
            },
            "memory": {
                "physical": {
                    "used": 42153271296,
                    "total": 67417227264
                },
                "swap": {
                    "used": 0,
                    "total": 2147479552
                }
            },
            "gc": {
                "G1 Young Generation": {
                    "total": 364,
                    "avgTime": 20.554945054945055,
                    "avgFrequency": 59993
                },
                "G1 Concurrent GC": {
                    "total": 244,
                    "avgTime": 7.610655737704918,
                    "avgFrequency": 89520
                },
                "G1 Old Generation": {
                    "total": 1,
                    "avgTime": 188,
                    "avgFrequency": 21844770
                }
            },
            "disk": {
                "used": 66855079936,
                "total": 1081101176832
            },
            "os": {
                "arch": "amd64",
                "version": "6.5.0-41-generic"
            },
            "java": {
                "vendor": "Eclipse Adoptium",
                "version": "21.0.3",
                "vendorVersion": "Temurin-21.0.3+9",
                "vmArgs": "-Xms128M -XX:MaxRAMPercentage=95.0 -Dterminal.jline=false -Dterminal.ansi=true"
            },
            "uptime": 21844958,
            "net": {
                "lo": {
                    "rxBytesPerSecond": {
                        "mean": 1.0666666666666667,
                        "max": 8,
                        "min": 0,
                        "median": 0,
                        "percentile95": 8
                    },
                    "txBytesPerSecond": {
                        "mean": 1.0666666666666667,
                        "max": 8,
                        "min": 0,
                        "median": 0,
                        "percentile95": 8
                    },
                    "rxPacketsPerSecond": {
                        "mean": 0,
                        "max": 0,
                        "min": 0,
                        "median": 0,
                        "percentile95": 0
                    },
                    "txPacketsPerSecond": {
                        "mean": 0,
                        "max": 0,
                        "min": 0,
                        "median": 0,
                        "percentile95": 0
                    }
                },
                "eth0": {
                    "rxBytesPerSecond": {
                        "mean": 2522,
                        "max": 3432,
                        "min": 2163,
                        "median": 2451,
                        "percentile95": 3432
                    },
                    "txBytesPerSecond": {
                        "mean": 21605,
                        "max": 42311,
                        "min": 4677,
                        "median": 19026,
                        "percentile95": 42311
                    },
                    "rxPacketsPerSecond": {
                        "mean": 36.46666666666667,
                        "max": 51,
                        "min": 29,
                        "median": 36,
                        "percentile95": 51
                    },
                    "txPacketsPerSecond": {
                        "mean": 40.53333333333333,
                        "max": 52,
                        "min": 34,
                        "median": 40,
                        "percentile95": 52
                    }
                }
            }
        },
        "serverConfigurations": {
            "server.properties": {
                "enable-jmx-monitoring": false,
                "rcon.port": 25575,
                "enable-command-block": false,
                "gamemode": "survival",
                "enable-query": false,
                "generator-settings": "{}",
                "enforce-secure-profile": true,
                "level-name": "world",
                "query.port": 25572,
                "pvp": true,
                "generate-structures": true,
                "max-chained-neighbor-updates": 1000000,
                "difficulty": "easy",
                "network-compression-threshold": 256,
                "max-tick-time": 60000,
                "require-resource-pack": false,
                "max-players": 20,
                "use-native-transport": true,
                "enable-status": true,
                "online-mode": false,
                "allow-flight": false,
                "initial-disabled-packs": "",
                "broadcast-rcon-to-ops": true,
                "view-distance": 10,
                "resource-pack-prompt": "",
                "bug-report-link": "",
                "allow-nether": true,
                "server-port": 25572,
                "enable-rcon": false,
                "sync-chunk-writes": true,
                "resource-pack-id": "",
                "op-permission-level": 4,
                "accepts-transfers": false,
                "prevent-proxy-connections": false,
                "hide-online-players": false,
                "entity-broadcast-range-percentage": 100,
                "simulation-distance": 10,
                "player-idle-timeout": 0,
                "debug": false,
                "force-gamemode": false,
                "rate-limit": 0,
                "hardcore": false,
                "white-list": false,
                "broadcast-console-to-ops": true,
                "region-file-compression": "deflate",
                "spawn-npcs": true,
                "spawn-animals": true,
                "log-ips": true,
                "function-permission-level": 2,
                "initial-enabled-packs": "vanilla",
                "level-type": "minecraft:normal",
                "text-filtering-config": "",
                "spawn-monsters": true,
                "enforce-whitelist": false,
                "resource-pack-sha1": "",
                "spawn-protection": 16,
                "max-world-size": 29999984
            },
            "bukkit.yml": {
                "settings": {
                    "allow-end": true,
                    "warn-on-overload": true,
                    "permissions-file": "permissions.yml",
                    "update-folder": "update",
                    "plugin-profiling": false,
                    "connection-throttle": 4000,
                    "query-plugins": true,
                    "deprecated-verbose": "default",
                    "minimum-api": "none",
                    "use-map-color-cache": true,
                    "compatibility": {
                        "allow-old-keys-in-registry": false
                    }
                },
                "spawn-limits": {
                    "monsters": 70,
                    "animals": 10,
                    "water-animals": 5,
                    "water-ambient": 20,
                    "water-underground-creature": 5,
                    "axolotls": 5,
                    "ambient": 15
                },
                "chunk-gc": {
                    "period-in-ticks": 600
                },
                "ticks-per": {
                    "animal-spawns": 400,
                    "monster-spawns": 1,
                    "water-spawns": 1,
                    "water-ambient-spawns": 1,
                    "water-underground-creature-spawns": 1,
                    "axolotl-spawns": 1,
                    "ambient-spawns": 1,
                    "autosave": 6000
                },
                "aliases": "now-in-commands.yml"
            },
            "spigot.yml": {
                "world-settings": {
                    "default": {
                        "below-zero-generation-in-existing-chunks": true,
                        "verbose": true,
                        "growth": {
                            "cactus-modifier": 100,
                            "cane-modifier": 100,
                            "melon-modifier": 100,
                            "mushroom-modifier": 100,
                            "pumpkin-modifier": 100,
                            "sapling-modifier": 100,
                            "beetroot-modifier": 100,
                            "carrot-modifier": 100,
                            "potato-modifier": 100,
                            "wheat-modifier": 100,
                            "netherwart-modifier": 100,
                            "vine-modifier": 100,
                            "cocoa-modifier": 100,
                            "bamboo-modifier": 100,
                            "sweetberry-modifier": 100,
                            "kelp-modifier": 100,
                            "twistingvines-modifier": 100,
                            "weepingvines-modifier": 100,
                            "cavevines-modifier": 100
                        },
                        "ticks-per": {
                            "hopper-transfer": 8,
                            "hopper-check": 1
                        },
                        "hopper-amount": 1,
                        "hopper-can-load-chunks": false,
                        "unload-frozen-chunks": false,
                        "merge-radius": {
                            "exp": 3.0,
                            "item": 2.5
                        },
                        "mob-spawn-range": 6,
                        "entity-activation-range": {
                            "animals": 32,
                            "monsters": 32,
                            "raiders": 48,
                            "misc": 16,
                            "tick-inactive-villagers": true,
                            "ignore-spectators": false
                        },
                        "entity-tracking-range": {
                            "players": 48,
                            "animals": 48,
                            "monsters": 48,
                            "misc": 32,
                            "display": 128,
                            "other": 64
                        },
                        "dragon-death-sound-radius": 0,
                        "hunger": {
                            "jump-walk-exhaustion": 0.05,
                            "jump-sprint-exhaustion": 0.2,
                            "combat-exhaustion": 0.1,
                            "regen-exhaustion": 6.0,
                            "swim-multiplier": 0.01,
                            "sprint-multiplier": 0.1,
                            "other-multiplier": 0.0
                        },
                        "max-tnt-per-tick": 100,
                        "max-tick-time": {
                            "tile": 50,
                            "entity": 50
                        },
                        "view-distance": "default",
                        "simulation-distance": "default",
                        "thunder-chance": 100000,
                        "item-despawn-rate": 6000,
                        "enable-zombie-pigmen-portal-spawns": true,
                        "arrow-despawn-rate": 1200,
                        "trident-despawn-rate": 1200,
                        "wither-spawn-sound-radius": 0,
                        "end-portal-sound-radius": 0,
                        "hanging-tick-frequency": 100,
                        "zombie-aggressive-towards-villager": true,
                        "nerf-spawner-mobs": false
                    }
                },
                "commands": {
                    "log": true,
                    "tab-complete": 0,
                    "send-namespaced": true,
                    "spam-exclusions": [
                        "/skill"
                    ],
                    "silent-commandblock-console": false,
                    "replace-commands": [
                        "setblock",
                        "summon",
                        "testforblock",
                        "tellraw"
                    ]
                },
                "settings": {
                    "bungeecord": false,
                    "sample-count": 12,
                    "player-shuffle": 0,
                    "user-cache-size": 1000,
                    "save-user-cache-on-stop-only": false,
                    "moved-wrongly-threshold": 0.0625,
                    "moved-too-quickly-multiplier": 10.0,
                    "timeout-time": 60,
                    "restart-on-crash": true,
                    "restart-script": "./start.sh",
                    "netty-threads": 4,
                    "attribute": {
                        "maxHealth": {
                            "max": 2048.0
                        },
                        "movementSpeed": {
                            "max": 2048.0
                        },
                        "attackDamage": {
                            "max": 2048.0
                        }
                    },
                    "log-villager-deaths": true,
                    "log-named-deaths": true,
                    "debug": false
                },
                "advancements": {
                    "disable-saving": false,
                    "disabled": [
                        "minecraft:story/disabled"
                    ]
                },
                "players": {
                    "disable-saving": false
                },
                "config-version": 12,
                "stats": {
                    "disable-saving": false
                }
            }
        },
        "threadDumper": {
            "type": 1,
            "ids": [
                36
            ]
        },
        "dataAggregator": {
            "type": 0,
            "threadGrouper": 1,
            "tickLengthThreshold": 0,
            "numberOfIncludedTicks": 0
        },
        "comment": "",
        "endTime": 1718961787283,
        "numberOfTicks": 423258,
        "plugins": {
            "simpletpa": {
                "name": "SimpleTpa",
                "version": "7.1"
            },
            "voicechat": {
                "name": "voicechat",
                "version": "2.5.16"
            },
            "skinsrestorer": {
                "name": "SkinsRestorer",
                "version": "15.0.15"
            },
            "spark": {
                "name": "spark",
                "version": "1.10.71"
            },
            "griefprevention": {
                "name": "GriefPrevention",
                "version": "16.18.3"
            }
        },
        "samplerMode": 0
    }
}